{"v":4,"entries":{"otp--docs":{"id":"otp--docs","title":"Otp","name":"Docs","importPath":"./src/components/otp/Otp.stories.tsx","type":"docs","tags":["dev","test","autodocs","Otp"],"storiesImports":[]},"otp--default":{"type":"story","id":"otp--default","name":"Default","title":"Otp","importPath":"./src/components/otp/Otp.stories.tsx","tags":["dev","test","autodocs","Otp"]},"otp--error-state":{"type":"story","id":"otp--error-state","name":"Error State","title":"Otp","importPath":"./src/components/otp/Otp.stories.tsx","tags":["dev","test","autodocs","Otp"]},"button--docs":{"id":"button--docs","title":"Button","name":"Docs","importPath":"./src/components/ui/button/Button.stories.tsx","type":"docs","tags":["dev","test","autodocs"],"storiesImports":[]},"button--default":{"type":"story","id":"button--default","name":"Default","title":"Button","importPath":"./src/components/ui/button/Button.stories.tsx","tags":["dev","test","autodocs"]},"button--prefix":{"type":"story","id":"button--prefix","name":"Prefix","title":"Button","importPath":"./src/components/ui/button/Button.stories.tsx","tags":["dev","test","autodocs"]},"checkbox--docs":{"id":"checkbox--docs","title":"Checkbox","name":"Docs","importPath":"./src/components/ui/checkbox/Checkbox.stories.tsx","type":"docs","tags":["dev","test","autodocs"],"storiesImports":[]},"checkbox--default":{"type":"story","id":"checkbox--default","name":"Default","title":"Checkbox","importPath":"./src/components/ui/checkbox/Checkbox.stories.tsx","tags":["dev","test","autodocs"]},"checkbox--checked":{"type":"story","id":"checkbox--checked","name":"Checked","title":"Checkbox","importPath":"./src/components/ui/checkbox/Checkbox.stories.tsx","tags":["dev","test","autodocs"]},"input--docs":{"id":"input--docs","title":"Input","name":"Docs","importPath":"./src/components/ui/input/Input.stories.tsx","type":"docs","tags":["dev","test","autodocs"],"storiesImports":[]},"input--default":{"type":"story","id":"input--default","name":"Default","title":"Input","importPath":"./src/components/ui/input/Input.stories.tsx","tags":["dev","test","autodocs"]},"input--prefix":{"type":"story","id":"input--prefix","name":"Prefix","title":"Input","importPath":"./src/components/ui/input/Input.stories.tsx","tags":["dev","test","autodocs"]},"input--error-state":{"type":"story","id":"input--error-state","name":"Error State","title":"Input","importPath":"./src/components/ui/input/Input.stories.tsx","tags":["dev","test","autodocs"]}}}
